eziocon/__init__.py
eziocon/oracle/__init__.py
eziocon/oracle/connection.py
eziocon/oracle/query_processor.py
eziocon/oracle/sdk.py
eziocon/sql/__init__.py
eziocon/sql/connection.py
eziocon/sql/query_processor.py
eziocon/sql/sdk.py
eziocon-0.1.3.dist-info/LICENSE
eziocon-0.1.3.dist-info/METADATA
eziocon-0.1.3.dist-info/WHEEL
eziocon-0.1.3.dist-info/top_level.txt
eziocon-0.1.3.dist-info/RECORD
